CHANGELOG.txt
LICENCE.txt
MANIFEST.in
README.txt
setup.py
topsis101803603/__init__.py
topsis101803603.egg-info/PKG-INFO
topsis101803603.egg-info/SOURCES.txt
topsis101803603.egg-info/dependency_links.txt
topsis101803603.egg-info/top_level.txt