Metadata-Version: 1.1
Name: topsis101803603
Version: 0.0.1
Summary: A very basic calculator
Home-page: UNKNOWN
Author: Joshua Lowe
Author-email: mahir007mahir@gmail.com
License: MIT
Keywords: topsis101803603
Platform: UNKNOWN
Classifier: Development Status :: 5 - Production/Stable
Classifier: Intended Audience :: Education
Classifier: Operating System :: Microsoft :: Windows :: Windows 10
Classifier: License :: OSI Approved :: MIT License
Classifier: Programming Language :: Python :: 3
